[{"league":"Argentina - Liga Profesional","filtered":{"profil":"Low Risk","general":{"home":{"teamName":"Gimnasia","winning":"57.14","loosing":"14.29","fixedPercentageForWinning":35,"fixedPercentageForLoosing":45,"winningAvg":"22.14","loosingAvg":"30.71","winningAvgDecision":1,"loosingAvgDecision":1},"away":{"teamName":"Aldosivi","winning":"21.43","loosing":"64.29","fixedPercentageForWinning":30,"fixedPercentageForLoosing":45,"winningAvg":"8.57","loosingAvg":"19.29","winningAvgDecision":1,"loosingAvgDecision":1}},"homeAway":{"home":{"teamName":"Gimnasia","winning":"83.33","loosing":"0.00","fixedPercentageForWinning":50,"fixedPercentageForLoosing":40,"winningAvg":"33.33","loosingAvg":"40.00","winningAvgDecision":1,"loosingAvgDecision":1},"away":{"teamName":"Aldosivi","winning":"14.29","loosing":"71.43","fixedPercentageForWinning":25,"fixedPercentageForLoosing":65,"winningAvg":"10.71","loosingAvg":"6.43","winningAvgDecision":1,"loosingAvgDecision":1}}},"generalResultHomeAway":{"homeGeneralResult":{"teamName":"Gimnasia","gamePlayed":14,"winning":8,"draw":4,"loosing":2,"winningPercentage":"57.14","drawPercentage":"28.57","loosingPercentage":"14.29"},"awayGeneralResult":{"teamName":"Aldosivi","gamePlayed":14,"winning":3,"draw":2,"loosing":9,"winningPercentage":"21.43","drawPercentage":"14.29","loosingPercentage":"64.29"},"homeResult":{"teamName":"Gimnasia","gamePlayed":"6","winning":"5","draw":"1","loosing":"0","winningPercentage":"83.33","drawPercentage":"16.67","loosingPercentage":"0.00"},"awayResult":{"teamName":"Aldosivi","gamePlayed":"7","winning":"1","draw":"1","loosing":"5","winningPercentage":"14.29","drawPercentage":"14.29","loosingPercentage":"71.43"}},"firstGoalStats":{}},{"league":"Finland - Kakkonen Group B","filtered":{"profil":"Low Risk","general":{"home":{"teamName":"GrIFK","winning":"41.18","loosing":"41.18","fixedPercentageForWinning":35,"fixedPercentageForLoosing":45,"winningAvg":"6.18","loosingAvg":"3.82","winningAvgDecision":1,"loosingAvgDecision":1},"away":{"teamName":"EPS","winning":"33.33","loosing":"44.44","fixedPercentageForWinning":30,"fixedPercentageForLoosing":45,"winningAvg":"-3.33","loosingAvg":"-0.56","winningAvgDecision":0,"loosingAvgDecision":0}},"homeAway":{"home":{"teamName":"GrIFK","winning":"50.00","loosing":"37.50","fixedPercentageForWinning":50,"fixedPercentageForLoosing":40,"winningAvg":"0.00","loosingAvg":"2.50","winningAvgDecision":1,"loosingAvgDecision":1},"away":{"teamName":"EPS","winning":"22.22","loosing":"55.56","fixedPercentageForWinning":25,"fixedPercentageForLoosing":65,"winningAvg":"2.78","loosingAvg":"-9.44","winningAvgDecision":1,"loosingAvgDecision":0}}},"generalResultHomeAway":{"homeGeneralResult":{"teamName":"GrIFK","gamePlayed":17,"winning":7,"draw":3,"loosing":7,"winningPercentage":"41.18","drawPercentage":"17.65","loosingPercentage":"41.18"},"awayGeneralResult":{"teamName":"EPS","gamePlayed":18,"winning":6,"draw":4,"loosing":8,"winningPercentage":"33.33","drawPercentage":"22.22","loosingPercentage":"44.44"},"homeResult":{"teamName":"GrIFK","gamePlayed":"8","winning":"4","draw":"1","loosing":"3","winningPercentage":"50.00","drawPercentage":"12.50","loosingPercentage":"37.50"},"awayResult":{"teamName":"EPS","gamePlayed":"9","winning":"2","draw":"2","loosing":"5","winningPercentage":"22.22","drawPercentage":"22.22","loosingPercentage":"55.56"}},"firstGoalStats":{}},{"league":"Finland - Kakkonen Group B","filtered":{"profil":"Low Risk","general":{"home":{"teamName":"Ilves-Kissat","winning":"50.00","loosing":"27.78","fixedPercentageForWinning":35,"fixedPercentageForLoosing":45,"winningAvg":"15.00","loosingAvg":"17.22","winningAvgDecision":1,"loosingAvgDecision":1},"away":{"teamName":"KaaPo","winning":"11.76","loosing":"82.35","fixedPercentageForWinning":30,"fixedPercentageForLoosing":45,"winningAvg":"18.24","loosingAvg":"37.35","winningAvgDecision":1,"loosingAvgDecision":1}},"homeAway":{"home":{"teamName":"Ilves-Kissat","winning":"55.56","loosing":"22.22","fixedPercentageForWinning":50,"fixedPercentageForLoosing":40,"winningAvg":"5.56","loosingAvg":"17.78","winningAvgDecision":1,"loosingAvgDecision":1},"away":{"teamName":"KaaPo","winning":"12.50","loosing":"75.00","fixedPercentageForWinning":25,"fixedPercentageForLoosing":65,"winningAvg":"12.50","loosingAvg":"10.00","winningAvgDecision":1,"loosingAvgDecision":1}}},"generalResultHomeAway":{"homeGeneralResult":{"teamName":"Ilves-Kissat","gamePlayed":18,"winning":9,"draw":4,"loosing":5,"winningPercentage":"50.00","drawPercentage":"22.22","loosingPercentage":"27.78"},"awayGeneralResult":{"teamName":"KaaPo","gamePlayed":17,"winning":2,"draw":1,"loosing":14,"winningPercentage":"11.76","drawPercentage":"5.88","loosingPercentage":"82.35"},"homeResult":{"teamName":"Ilves-Kissat","gamePlayed":"9","winning":"5","draw":"2","loosing":"2","winningPercentage":"55.56","drawPercentage":"22.22","loosingPercentage":"22.22"},"awayResult":{"teamName":"KaaPo","gamePlayed":"8","winning":"1","draw":"1","loosing":"6","winningPercentage":"12.50","drawPercentage":"12.50","loosingPercentage":"75.00"}},"firstGoalStats":{}},{"league":"Malawi - Super League","filtered":{"profil":"Low Risk","general":{"home":{"teamName":"Blue Eagles","winning":"61.11","loosing":"5.56","fixedPercentageForWinning":35,"fixedPercentageForLoosing":45,"winningAvg":"26.11","loosingAvg":"39.44","winningAvgDecision":1,"loosingAvgDecision":1},"away":{"teamName":"Sable Farming","winning":"16.67","loosing":"50.00","fixedPercentageForWinning":30,"fixedPercentageForLoosing":45,"winningAvg":"13.33","loosingAvg":"5.00","winningAvgDecision":1,"loosingAvgDecision":1}},"homeAway":{"home":{"teamName":"Blue Eagles","winning":"55.56","loosing":"0.00","fixedPercentageForWinning":50,"fixedPercentageForLoosing":40,"winningAvg":"5.56","loosingAvg":"40.00","winningAvgDecision":1,"loosingAvgDecision":1},"away":{"teamName":"Sable Farming","winning":"12.50","loosing":"62.50","fixedPercentageForWinning":25,"fixedPercentageForLoosing":65,"winningAvg":"12.50","loosingAvg":"-2.50","winningAvgDecision":1,"loosingAvgDecision":0}}},"generalResultHomeAway":{"homeGeneralResult":{"teamName":"Blue Eagles","gamePlayed":18,"winning":11,"draw":6,"loosing":1,"winningPercentage":"61.11","drawPercentage":"33.33","loosingPercentage":"5.56"},"awayGeneralResult":{"teamName":"Sable Farming","gamePlayed":18,"winning":3,"draw":6,"loosing":9,"winningPercentage":"16.67","drawPercentage":"33.33","loosingPercentage":"50.00"},"homeResult":{"teamName":"Blue Eagles","gamePlayed":"9","winning":"5","draw":"4","loosing":"0","winningPercentage":"55.56","drawPercentage":"44.44","loosingPercentage":"0.00"},"awayResult":{"teamName":"Sable Farming","gamePlayed":"8","winning":"1","draw":"2","loosing":"5","winningPercentage":"12.50","drawPercentage":"25.00","loosingPercentage":"62.50"}},"firstGoalStats":{}},{"league":"Malaysia - Premier League","filtered":{"profil":"Low Risk","general":{"home":{"teamName":"Kuching","winning":"53.33","loosing":"26.67","fixedPercentageForWinning":35,"fixedPercentageForLoosing":45,"winningAvg":"18.33","loosingAvg":"18.33","winningAvgDecision":1,"loosingAvgDecision":1},"away":{"teamName":"Selangor B","winning":"20.00","loosing":"53.33","fixedPercentageForWinning":30,"fixedPercentageForLoosing":45,"winningAvg":"10.00","loosingAvg":"8.33","winningAvgDecision":1,"loosingAvgDecision":1}},"homeAway":{"home":{"teamName":"Kuching","winning":"71.43","loosing":"14.29","fixedPercentageForWinning":50,"fixedPercentageForLoosing":40,"winningAvg":"21.43","loosingAvg":"25.71","winningAvgDecision":1,"loosingAvgDecision":1},"away":{"teamName":"Selangor B","winning":"28.57","loosing":"57.14","fixedPercentageForWinning":25,"fixedPercentageForLoosing":65,"winningAvg":"-3.57","loosingAvg":"-7.86","winningAvgDecision":0,"loosingAvgDecision":0}}},"generalResultHomeAway":{"homeGeneralResult":{"teamName":"Kuching","gamePlayed":15,"winning":8,"draw":3,"loosing":4,"winningPercentage":"53.33","drawPercentage":"20.00","loosingPercentage":"26.67"},"awayGeneralResult":{"teamName":"Selangor B","gamePlayed":15,"winning":3,"draw":4,"loosing":8,"winningPercentage":"20.00","drawPercentage":"26.67","loosingPercentage":"53.33"},"homeResult":{"teamName":"Kuching","gamePlayed":"7","winning":"5","draw":"1","loosing":"1","winningPercentage":"71.43","drawPercentage":"14.29","loosingPercentage":"14.29"},"awayResult":{"teamName":"Selangor B","gamePlayed":"7","winning":"2","draw":"1","loosing":"4","winningPercentage":"28.57","drawPercentage":"14.29","loosingPercentage":"57.14"}},"firstGoalStats":{}},{"league":"Uruguay - Segunda Division","filtered":{"profil":"Low Risk","general":{"home":{"teamName":"Miramar Misione","winning":"37.50","loosing":"31.25","fixedPercentageForWinning":35,"fixedPercentageForLoosing":45,"winningAvg":"2.50","loosingAvg":"13.75","winningAvgDecision":1,"loosingAvgDecision":1},"away":{"teamName":"Central Espanol","winning":"18.75","loosing":"37.50","fixedPercentageForWinning":30,"fixedPercentageForLoosing":45,"winningAvg":"11.25","loosingAvg":"-7.50","winningAvgDecision":1,"loosingAvgDecision":0}},"homeAway":{"home":{"teamName":"Miramar Misione","winning":"42.86","loosing":"28.57","fixedPercentageForWinning":50,"fixedPercentageForLoosing":40,"winningAvg":"-7.14","loosingAvg":"11.43","winningAvgDecision":0,"loosingAvgDecision":1},"away":{"teamName":"Central Espanol","winning":"0.00","loosing":"62.50","fixedPercentageForWinning":25,"fixedPercentageForLoosing":65,"winningAvg":"25.00","loosingAvg":"-2.50","winningAvgDecision":1,"loosingAvgDecision":0}}},"generalResultHomeAway":{"homeGeneralResult":{"teamName":"Miramar Misione","gamePlayed":16,"winning":6,"draw":5,"loosing":5,"winningPercentage":"37.50","drawPercentage":"31.25","loosingPercentage":"31.25"},"awayGeneralResult":{"teamName":"Central Espanol","gamePlayed":16,"winning":3,"draw":7,"loosing":6,"winningPercentage":"18.75","drawPercentage":"43.75","loosingPercentage":"37.50"},"homeResult":{"teamName":"Miramar Misione","gamePlayed":"7","winning":"3","draw":"2","loosing":"2","winningPercentage":"42.86","drawPercentage":"28.57","loosingPercentage":"28.57"},"awayResult":{"teamName":"Central Espanol","gamePlayed":"8","winning":"0","draw":"3","loosing":"5","winningPercentage":"0.00","drawPercentage":"37.50","loosingPercentage":"62.50"}},"firstGoalStats":{}}]