[{"league":"Bolivia - Primera Div. - Clausura","filtered":{"profil":"Low Risk","general":{"home":{"teamName":"Always Ready","winning":"80.00","loosing":"10.00","fixedPercentageForWinning":42,"fixedPercentageForLoosing":35,"winningAvg":"38.00","loosingAvg":"25.00","winningAvgDecision":1,"loosingAvgDecision":1},"away":{"teamName":"Wilstermann","winning":"36.36","loosing":"54.55","fixedPercentageForWinning":35,"fixedPercentageForLoosing":28,"winningAvg":"-1.36","loosingAvg":"26.55","winningAvgDecision":0,"loosingAvgDecision":1}},"homeAway":{"home":{"teamName":"Always Ready","winning":"100.00","loosing":"0.00","fixedPercentageForWinning":57,"fixedPercentageForLoosing":28,"winningAvg":"43.00","loosingAvg":"28.00","winningAvgDecision":1,"loosingAvgDecision":1},"away":{"teamName":"Wilstermann","winning":"20.00","loosing":"80.00","fixedPercentageForWinning":15,"fixedPercentageForLoosing":40,"winningAvg":"-5.00","loosingAvg":"40.00","winningAvgDecision":0,"loosingAvgDecision":1}}},"generalResultHomeAway":{"homeGeneralResult":{"teamName":"Always Ready","gamePlayed":10,"winning":8,"draw":1,"loosing":1,"winningPercentage":"80.00","drawPercentage":"10.00","loosingPercentage":"10.00"},"awayGeneralResult":{"teamName":"Wilstermann","gamePlayed":11,"winning":4,"draw":1,"loosing":6,"winningPercentage":"36.36","drawPercentage":"9.09","loosingPercentage":"54.55"},"homeResult":{"teamName":"Always Ready","gamePlayed":"6","winning":"6","draw":"0","loosing":"0","winningPercentage":"100.00","drawPercentage":"0.00","loosingPercentage":"0.00"},"awayResult":{"teamName":"Wilstermann","gamePlayed":"5","winning":"1","draw":"0","loosing":"4","winningPercentage":"20.00","drawPercentage":"0.00","loosingPercentage":"80.00"}},"firstGoalStats":{}},{"league":"Chile - Primera B","filtered":{"profil":"Low Risk","general":{"home":{"teamName":"Cobreloa","winning":"56.52","loosing":"17.39","fixedPercentageForWinning":42,"fixedPercentageForLoosing":35,"winningAvg":"14.52","loosingAvg":"17.61","winningAvgDecision":1,"loosingAvgDecision":1},"away":{"teamName":"Melipilla","winning":"27.27","loosing":"45.45","fixedPercentageForWinning":35,"fixedPercentageForLoosing":28,"winningAvg":"7.73","loosingAvg":"17.45","winningAvgDecision":1,"loosingAvgDecision":1}},"homeAway":{"home":{"teamName":"Cobreloa","winning":"90.91","loosing":"0.00","fixedPercentageForWinning":57,"fixedPercentageForLoosing":28,"winningAvg":"33.91","loosingAvg":"28.00","winningAvgDecision":1,"loosingAvgDecision":1},"away":{"teamName":"Melipilla","winning":"9.09","loosing":"54.55","fixedPercentageForWinning":15,"fixedPercentageForLoosing":40,"winningAvg":"5.91","loosingAvg":"14.55","winningAvgDecision":1,"loosingAvgDecision":1}}},"generalResultHomeAway":{"homeGeneralResult":{"teamName":"Cobreloa","gamePlayed":23,"winning":13,"draw":6,"loosing":4,"winningPercentage":"56.52","drawPercentage":"26.09","loosingPercentage":"17.39"},"awayGeneralResult":{"teamName":"Melipilla","gamePlayed":22,"winning":6,"draw":6,"loosing":10,"winningPercentage":"27.27","drawPercentage":"27.27","loosingPercentage":"45.45"},"homeResult":{"teamName":"Cobreloa","gamePlayed":"11","winning":"10","draw":"1","loosing":"0","winningPercentage":"90.91","drawPercentage":"9.09","loosingPercentage":"0.00"},"awayResult":{"teamName":"Melipilla","gamePlayed":"11","winning":"1","draw":"4","loosing":"6","winningPercentage":"9.09","drawPercentage":"36.36","loosingPercentage":"54.55"}},"firstGoalStats":{}},{"league":"Georgia - Erovnuli Liga","filtered":{"profil":"Low Risk","general":{"home":{"teamName":"Dila Gori","winning":"45.45","loosing":"36.36","fixedPercentageForWinning":42,"fixedPercentageForLoosing":35,"winningAvg":"3.45","loosingAvg":"-1.36","winningAvgDecision":1,"loosingAvgDecision":0},"away":{"teamName":"Sioni Bolsini","winning":"22.73","loosing":"45.45","fixedPercentageForWinning":35,"fixedPercentageForLoosing":28,"winningAvg":"12.27","loosingAvg":"17.45","winningAvgDecision":1,"loosingAvgDecision":1}},"homeAway":{"home":{"teamName":"Dila Gori","winning":"72.73","loosing":"18.18","fixedPercentageForWinning":57,"fixedPercentageForLoosing":28,"winningAvg":"15.73","loosingAvg":"9.82","winningAvgDecision":1,"loosingAvgDecision":1},"away":{"teamName":"Sioni Bolsini","winning":"18.18","loosing":"63.64","fixedPercentageForWinning":15,"fixedPercentageForLoosing":40,"winningAvg":"-3.18","loosingAvg":"23.64","winningAvgDecision":0,"loosingAvgDecision":1}}},"generalResultHomeAway":{"homeGeneralResult":{"teamName":"Dila Gori","gamePlayed":22,"winning":10,"draw":4,"loosing":8,"winningPercentage":"45.45","drawPercentage":"18.18","loosingPercentage":"36.36"},"awayGeneralResult":{"teamName":"Sioni Bolsini","gamePlayed":22,"winning":5,"draw":7,"loosing":10,"winningPercentage":"22.73","drawPercentage":"31.82","loosingPercentage":"45.45"},"homeResult":{"teamName":"Dila Gori","gamePlayed":"11","winning":"8","draw":"1","loosing":"2","winningPercentage":"72.73","drawPercentage":"9.09","loosingPercentage":"18.18"},"awayResult":{"teamName":"Sioni Bolsini","gamePlayed":"11","winning":"2","draw":"2","loosing":"7","winningPercentage":"18.18","drawPercentage":"18.18","loosingPercentage":"63.64"}},"firstGoalStats":{}},{"league":"Lithuania - 1st League","filtered":{"profil":"Low Risk","general":{"home":{"teamName":"Silas","winning":"52.63","loosing":"26.32","fixedPercentageForWinning":42,"fixedPercentageForLoosing":35,"winningAvg":"10.63","loosingAvg":"8.68","winningAvgDecision":1,"loosingAvgDecision":1},"away":{"teamName":"Riteriai B","winning":"23.53","loosing":"35.29","fixedPercentageForWinning":35,"fixedPercentageForLoosing":28,"winningAvg":"11.47","loosingAvg":"7.29","winningAvgDecision":1,"loosingAvgDecision":1}},"homeAway":{"home":{"teamName":"Silas","winning":"60.00","loosing":"20.00","fixedPercentageForWinning":57,"fixedPercentageForLoosing":28,"winningAvg":"3.00","loosingAvg":"8.00","winningAvgDecision":1,"loosingAvgDecision":1},"away":{"teamName":"Riteriai B","winning":"20.00","loosing":"40.00","fixedPercentageForWinning":15,"fixedPercentageForLoosing":40,"winningAvg":"-5.00","loosingAvg":"0.00","winningAvgDecision":0,"loosingAvgDecision":1}}},"generalResultHomeAway":{"homeGeneralResult":{"teamName":"Silas","gamePlayed":19,"winning":10,"draw":4,"loosing":5,"winningPercentage":"52.63","drawPercentage":"21.05","loosingPercentage":"26.32"},"awayGeneralResult":{"teamName":"Riteriai B","gamePlayed":17,"winning":4,"draw":7,"loosing":6,"winningPercentage":"23.53","drawPercentage":"41.18","loosingPercentage":"35.29"},"homeResult":{"teamName":"Silas","gamePlayed":"10","winning":"6","draw":"2","loosing":"2","winningPercentage":"60.00","drawPercentage":"20.00","loosingPercentage":"20.00"},"awayResult":{"teamName":"Riteriai B","gamePlayed":"10","winning":"2","draw":"4","loosing":"4","winningPercentage":"20.00","drawPercentage":"40.00","loosingPercentage":"40.00"}},"firstGoalStats":{}}]