[{"league":"Finland - Veikkausliiga","filtered":{"profil":"Low Risk","general":{"home":{"teamName":"Honka","winning":"61.11","loosing":"16.67","fixedPercentageForWinning":60,"fixedPercentageForLoosing":20,"winningAvg":"1.11","loosingAvg":"3.33","winningAvgDecision":1,"loosingAvgDecision":1},"away":{"teamName":"HIFK","winning":"5.56","loosing":"66.67","fixedPercentageForWinning":35,"fixedPercentageForLoosing":30,"winningAvg":"29.44","loosingAvg":"36.67","winningAvgDecision":1,"loosingAvgDecision":1}},"homeAway":{"home":{"teamName":"Honka","winning":"75.00","loosing":"0.00","fixedPercentageForWinning":60,"fixedPercentageForLoosing":20,"winningAvg":"15.00","loosingAvg":"20.00","winningAvgDecision":1,"loosingAvgDecision":1},"away":{"teamName":"HIFK","winning":"12.50","loosing":"37.50","fixedPercentageForWinning":35,"fixedPercentageForLoosing":25,"winningAvg":"22.50","loosingAvg":"12.50","winningAvgDecision":1,"loosingAvgDecision":1}}},"generalResultHomeAway":{"homeGeneralResult":{"teamName":"Honka","gamePlayed":18,"winning":11,"draw":4,"loosing":3,"winningPercentage":"61.11","drawPercentage":"22.22","loosingPercentage":"16.67"},"awayGeneralResult":{"teamName":"HIFK","gamePlayed":18,"winning":1,"draw":5,"loosing":12,"winningPercentage":"5.56","drawPercentage":"27.78","loosingPercentage":"66.67"},"homeResult":{"teamName":"Honka","gamePlayed":"8","winning":"6","draw":"2","loosing":"0","winningPercentage":"75.00","drawPercentage":"25.00","loosingPercentage":"0.00"},"awayResult":{"teamName":"HIFK","gamePlayed":"8","winning":"1","draw":"4","loosing":"3","winningPercentage":"12.50","drawPercentage":"50.00","loosingPercentage":"37.50"}},"firstGoalStats":{}},{"league":"Norway - 1st Division","filtered":{"profil":"Low Risk","general":{"home":{"teamName":"Ranheim","winning":"55.00","loosing":"20.00","fixedPercentageForWinning":60,"fixedPercentageForLoosing":20,"winningAvg":"-5.00","loosingAvg":"0.00","winningAvgDecision":0,"loosingAvgDecision":1},"away":{"teamName":"Bryne","winning":"25.00","loosing":"55.00","fixedPercentageForWinning":35,"fixedPercentageForLoosing":30,"winningAvg":"10.00","loosingAvg":"25.00","winningAvgDecision":1,"loosingAvgDecision":1}},"homeAway":{"home":{"teamName":"Ranheim","winning":"60.00","loosing":"20.00","fixedPercentageForWinning":60,"fixedPercentageForLoosing":20,"winningAvg":"0.00","loosingAvg":"0.00","winningAvgDecision":1,"loosingAvgDecision":1},"away":{"teamName":"Bryne","winning":"20.00","loosing":"70.00","fixedPercentageForWinning":35,"fixedPercentageForLoosing":25,"winningAvg":"15.00","loosingAvg":"45.00","winningAvgDecision":1,"loosingAvgDecision":1}}},"generalResultHomeAway":{"homeGeneralResult":{"teamName":"Ranheim","gamePlayed":20,"winning":11,"draw":5,"loosing":4,"winningPercentage":"55.00","drawPercentage":"25.00","loosingPercentage":"20.00"},"awayGeneralResult":{"teamName":"Bryne","gamePlayed":20,"winning":5,"draw":4,"loosing":11,"winningPercentage":"25.00","drawPercentage":"20.00","loosingPercentage":"55.00"},"homeResult":{"teamName":"Ranheim","gamePlayed":"10","winning":"6","draw":"2","loosing":"2","winningPercentage":"60.00","drawPercentage":"20.00","loosingPercentage":"20.00"},"awayResult":{"teamName":"Bryne","gamePlayed":"10","winning":"2","draw":"1","loosing":"7","winningPercentage":"20.00","drawPercentage":"10.00","loosingPercentage":"70.00"}},"firstGoalStats":{}},{"league":"Sweden - Allsvenskan","filtered":{"profil":"Low Risk","general":{"home":{"teamName":"Hammarby","winning":"61.11","loosing":"22.22","fixedPercentageForWinning":60,"fixedPercentageForLoosing":20,"winningAvg":"1.11","loosingAvg":"-2.22","winningAvgDecision":1,"loosingAvgDecision":0},"away":{"teamName":"Degerfors","winning":"16.67","loosing":"66.67","fixedPercentageForWinning":35,"fixedPercentageForLoosing":30,"winningAvg":"18.33","loosingAvg":"36.67","winningAvgDecision":1,"loosingAvgDecision":1}},"homeAway":{"home":{"teamName":"Hammarby","winning":"60.00","loosing":"10.00","fixedPercentageForWinning":60,"fixedPercentageForLoosing":20,"winningAvg":"0.00","loosingAvg":"10.00","winningAvgDecision":1,"loosingAvgDecision":1},"away":{"teamName":"Degerfors","winning":"11.11","loosing":"88.89","fixedPercentageForWinning":35,"fixedPercentageForLoosing":25,"winningAvg":"23.89","loosingAvg":"63.89","winningAvgDecision":1,"loosingAvgDecision":1}}},"generalResultHomeAway":{"homeGeneralResult":{"teamName":"Hammarby","gamePlayed":18,"winning":11,"draw":3,"loosing":4,"winningPercentage":"61.11","drawPercentage":"16.67","loosingPercentage":"22.22"},"awayGeneralResult":{"teamName":"Degerfors","gamePlayed":18,"winning":3,"draw":3,"loosing":12,"winningPercentage":"16.67","drawPercentage":"16.67","loosingPercentage":"66.67"},"homeResult":{"teamName":"Hammarby","gamePlayed":"10","winning":"6","draw":"3","loosing":"1","winningPercentage":"60.00","drawPercentage":"30.00","loosingPercentage":"10.00"},"awayResult":{"teamName":"Degerfors","gamePlayed":"9","winning":"1","draw":"0","loosing":"8","winningPercentage":"11.11","drawPercentage":"0.00","loosingPercentage":"88.89"}},"firstGoalStats":{}},{"league":"Sweden - Div 1 - Södra","filtered":{"profil":"Low Risk","general":{"home":{"teamName":"Angelholm","winning":"50.00","loosing":"27.78","fixedPercentageForWinning":60,"fixedPercentageForLoosing":20,"winningAvg":"-10.00","loosingAvg":"-7.78","winningAvgDecision":0,"loosingAvgDecision":0},"away":{"teamName":"IFK Malmo","winning":"5.56","loosing":"88.89","fixedPercentageForWinning":35,"fixedPercentageForLoosing":30,"winningAvg":"29.44","loosingAvg":"58.89","winningAvgDecision":1,"loosingAvgDecision":1}},"homeAway":{"home":{"teamName":"Angelholm","winning":"66.67","loosing":"0.00","fixedPercentageForWinning":60,"fixedPercentageForLoosing":20,"winningAvg":"6.67","loosingAvg":"20.00","winningAvgDecision":1,"loosingAvgDecision":1},"away":{"teamName":"IFK Malmo","winning":"11.11","loosing":"88.89","fixedPercentageForWinning":35,"fixedPercentageForLoosing":25,"winningAvg":"23.89","loosingAvg":"63.89","winningAvgDecision":1,"loosingAvgDecision":1}}},"generalResultHomeAway":{"homeGeneralResult":{"teamName":"Angelholm","gamePlayed":18,"winning":9,"draw":4,"loosing":5,"winningPercentage":"50.00","drawPercentage":"22.22","loosingPercentage":"27.78"},"awayGeneralResult":{"teamName":"IFK Malmo","gamePlayed":18,"winning":1,"draw":1,"loosing":16,"winningPercentage":"5.56","drawPercentage":"5.56","loosingPercentage":"88.89"},"homeResult":{"teamName":"Angelholm","gamePlayed":"9","winning":"6","draw":"3","loosing":"0","winningPercentage":"66.67","drawPercentage":"33.33","loosingPercentage":"0.00"},"awayResult":{"teamName":"IFK Malmo","gamePlayed":"9","winning":"1","draw":"0","loosing":"8","winningPercentage":"11.11","drawPercentage":"0.00","loosingPercentage":"88.89"}},"firstGoalStats":{}}]